[
  {
    "id": "a1",
    "name": "Nuget",
    "type": "Kissa",
    "age": 2,
    "breed": "Bengali",
    "description": "Iloinen ja leikkisä kissa. Soveltuu rauhalliseen kotiin.",
    "imageUrl": "https://basepaws.com/_next/image?url=https%3A%2F%2Fimages.ctfassets.net%2Fqj2yxv39d6ig%2F4Sz2RNDS3EF7i5TmMYrZXv%2F8dc5950086ae878ac844632153e74224%2Ffree-photo-of-close-up-of-a-bengal-cat.jpeg&w=1080&q=75",
    "status": "Saatavilla"
  },
  {
    "id": "a2",
    "name": "Jaden",
    "type": "Koira",
    "age": 9,
    "breed": "Labradorinnoutaja",
    "description": "Rauhallinen vanhempi herra, nauttii pitkistä kävelyistä ja rapsutuksista. Ei sovellu pieniin asuntoihin.",
    "imageUrl": "https://images.cdn.yle.fi/image/upload/ar_0.7494145199063232,c_fill,g_faces,h_1601,w_1200/dpr_1.0/q_auto:eco/f_auto/fl_lossy/v1699293233/39-11967176549278500b2c",
    "status": "Saatavilla"
  },
  {
    "id": "a3",
    "name": "Mimi",
    "type": "Lintu",
    "age": 5,
    "breed": "Harmaapapukaija",
    "description": "Älykäs ja puhelias lintu, tarvitsee paljon tilaa ja virikkeitä.",
    "imageUrl": "https://upload.wikimedia.org/wikipedia/commons/thumb/b/ba/Psittacus_erithacus_qtl1.jpg/250px-Psittacus_erithacus_qtl1.jpg",
    "status": "Saatavilla"
  },
  {
    "id": "a4",
    "name": "Titi",
    "type": "Hiiri",
    "age": 0,
    "breed": "Afrikkalainen kääpiöhiiri",
    "description": "Pieni ja nopea, adoptoidaan vain pariskuntana.",
    "imageUrl": "https://hiiret.fi/pics/afrikka01.jpg",
    "status": "Saatavilla"
  },
  {
    "id": "a5",
    "name": "Lumi",
    "type": "Kissa",
    "age": 8,
    "breed": "Siperiankissa",
    "description": "Erittäin pitkäturkkainen, vaatii päivittäisen harjauksen. Sopii allergikoille.",
    "imageUrl": "https://www.kissarodut.fi/wp-content/uploads/2023/06/siperiankissa.jpg",
    "status": "Varattu"
  },
  {
    "id": "a6",
    "name": "Zoey",
    "type": "Lisko",
    "age": 2,
    "breed": "Parta-agama",
    "description": "Tarvitsee lämpimän terraarion ja UVB-valon. Helppohoitoinen harrastelijan lisko.",
    "imageUrl": "https://www.akvaariolinna.fi/storage/editor_files/Materiaalit/Sis%C3%A4lt%C3%B6sivujen%20kuvat/Hoito%20ohjeet/Parta-agama%203.jpg",
    "status": "Saatavilla"
  }
]